LICENSE
README.md
setup.cfg
setup.py
dipylon/__init__.py
dipylon/coincodex.py
dipylon/coindesk.py
dipylon/coinmarketcap.py
dipylon/earningswhispers.py
dipylon/nasdaq.py
dipylon/quiverquant.py
dipylon/unusualwhales.py
dipylon/yahoofinance.py
dipylon.egg-info/PKG-INFO
dipylon.egg-info/SOURCES.txt
dipylon.egg-info/dependency_links.txt
dipylon.egg-info/requires.txt
dipylon.egg-info/top_level.txt
scripts/dipylon